MANIFEST.in
README.txt
setup.cfg
setup.py
yxspkg_wget.py
yxspkg_wget.egg-info/PKG-INFO
yxspkg_wget.egg-info/SOURCES.txt
yxspkg_wget.egg-info/dependency_links.txt
yxspkg_wget.egg-info/entry_points.txt
yxspkg_wget.egg-info/top_level.txt