Metadata-Version: 1.1
Name: yxspkg-wget
Version: 0.1.2
Summary: A simple application to download images from website with a url
Home-page: https://github.com/blacksong
Author: Blacksong
Author-email: blacksong@yeah.net
License: UNKNOWN
Platform: any
Classifier: Programming Language :: Python :: 3
Classifier: Operating System :: OS Independent
Classifier: Topic :: Software Development :: Libraries :: Python Modules
